{"cameraMode":{"drawMode":0,"name":"Shaded","section":"Shading Mode"},"sceneLighting":false,"audioPlay":false,"sceneViewState":{"showFog":false,"showMaterialUpdate":false,"showSkybox":false,"showFlares":false,"showImageEffects":false,"showParticleSystems":false,"showVisualEffectGraphs":true,"m_FxEnabled":false},"in2DMode":false,"pivot":{"x":-8.939998626708985,"y":12.417081832885743,"z":-2.6853017807006838},"rotation":{"x":-0.03732587397098541,"y":0.9335199594497681,"z":-0.10209742933511734,"w":-0.3417920768260956},"size":6.215497970581055,"orthographic":false}